layerbrain/__init__.py
layerbrain-0.1.0.dist-info/LICENSE
layerbrain-0.1.0.dist-info/METADATA
layerbrain-0.1.0.dist-info/WHEEL
layerbrain-0.1.0.dist-info/top_level.txt
layerbrain-0.1.0.dist-info/RECORD
