Metadata-Version: 2.1
Name: layerbrain
Version: 0.1.0
Summary: Python library for interacting with the Layerbrain API.
Home-page: https://github.com/layerbrain/layerbrain-python
Author: Layerbrain
Author-email: support@layerbrain.com
Classifier: Programming Language :: Python :: 3
Classifier: License :: OSI Approved :: MIT License
Classifier: Operating System :: OS Independent
Requires-Python: >=3.6
License-File: LICENSE
